zshell/__init__.py
zshell/_auto_reply_tool.py
zshell/_re_type.py
zshell/auto_reply.py
zshell/terminal.py
zshell-0.1.0.dist-info/LICENSE
zshell-0.1.0.dist-info/METADATA
zshell-0.1.0.dist-info/WHEEL
zshell-0.1.0.dist-info/top_level.txt
zshell-0.1.0.dist-info/RECORD
