Metadata-Version: 2.1
Name: zshell
Version: 0.1.0
Summary: shell自动化模块
Home-page: https://pypi.org/project/zshell
Author: zlyuan
Author-email: 1277260932@qq.com
License: GNU GENERAL PUBLIC LICENSE
Platform: all
Classifier: Environment :: Web Environment
Classifier: Intended Audience :: Developers
Classifier: Operating System :: OS Independent
Classifier: Programming Language :: Python
Classifier: Programming Language :: Python :: 3
Requires-Dist: paramiko
